bcdp/__init__.py
bcdp/adapters.py
bcdp/bounds.py
bcdp/constants.py
bcdp/ensemble.py
bcdp/extractors.py
bcdp/metrics.py
bcdp/processing.py
bcdp/registry.py
bcdp/regridder.py
bcdp/sources.py
bcdp/utils.py
bcdp-0.1.5.dist-info/LICENSE
bcdp-0.1.5.dist-info/METADATA
bcdp-0.1.5.dist-info/WHEEL
bcdp-0.1.5.dist-info/top_level.txt
bcdp-0.1.5.dist-info/RECORD
