Metadata-Version: 2.1
Name: bcdp
Version: 0.1.5
Summary: Big Climate Data Pipeline
Home-page: UNKNOWN
Author: Alex Goodman
Author-email: UNKNOWN
License: UNKNOWN
Platform: UNKNOWN
